MANIFEST.in
setup.py
tzutil/__init__.py
tzutil/b64uuid.py
tzutil/cached_req.py
tzutil/cached_spider.py
tzutil/cout.py
tzutil/csv_li.py
tzutil/day.py
tzutil/dirreplace.py
tzutil/extract.py
tzutil/import_json.py
tzutil/ob.py
tzutil/req.py
tzutil/retry.py
tzutil/smtp.py
tzutil/spider.py
tzutil/tco.py
tzutil/unescape.py
tzutil/url_short.py
tzutil.egg-info/PKG-INFO
tzutil.egg-info/SOURCES.txt
tzutil.egg-info/dependency_links.txt
tzutil.egg-info/not-zip-safe
tzutil.egg-info/top_level.txt
tzutil/currency/__init__.py
tzutil/currency/const.py
tzutil/db/__init__.py
tzutil/db/pg/__init__.py
tzutil/db/pg/table_iter.py
tzutil/db/pg/table_iter_for_update.py
tzutil/db/pg/pgwrap/__init__.py
tzutil/db/pg/pgwrap/cli.py
tzutil/db/pg/pgwrap/db.py
tzutil/db/pg/pgwrap/sqlop.py
tzutil/txt/__init__.py
tzutil/txt/cn.py
tzutil/txt/html.py