Metadata-Version: 1.0
Name: tzutil
Version: 0.5.3
Summary: Some common use functions
Home-page: https://gitee.com/TqLj/tzutil
Author: Lerry
Author-email: zsp042@gmail.com
License: UNKNOWN
Platform: UNKNOWN
